ptinjector/__init__.py
ptinjector/_version.py
ptinjector/ptinjector.py
ptinjector/definitions/403_bypass.json
ptinjector/definitions/__init__.py
ptinjector/definitions/_loader.py
ptinjector/definitions/_template.json
ptinjector/definitions/crlf.json
ptinjector/definitions/fpd.json
ptinjector/definitions/function_injection.json
ptinjector/definitions/hhi.json
ptinjector/definitions/lfi.json
ptinjector/definitions/rce.json
ptinjector/definitions/rfi.json
ptinjector/definitions/sqli_boolean.json
ptinjector/definitions/sqli_error.json
ptinjector/definitions/sqli_time.json
ptinjector/definitions/sqli_union.json
ptinjector/definitions/ssi.json
ptinjector/definitions/ssrf.json
ptinjector/definitions/ssti.json
ptinjector/definitions/xss.json
ptinjector/definitions/__pycache__/__init__.cpython-313.pyc
ptinjector/definitions/__pycache__/_loader.cpython-313.pyc
ptinjector/server/__init__.py
ptinjector/server/app.py
ptinjector/server/config.py
ptinjector-0.0.11.dist-info/licenses/LICENSE
ptinjector-0.0.11.dist-info/METADATA
ptinjector-0.0.11.dist-info/WHEEL
ptinjector-0.0.11.dist-info/entry_points.txt
ptinjector-0.0.11.dist-info/top_level.txt
ptinjector-0.0.11.dist-info/RECORD
